{
  "version": "1778926897582",
  "timestamp": "2026-05-16T12:21:37.581989+02:00",
  "config": {
    "maxPerTrade": 5.0,
    "maxOpenPositions": 3.0,
    "riskPerTrade": 0.125,
    "softStopPct": 0.15,
    "hardStopPct": 0.25,
    "trailingStopPct": 0.2,
    "timeLimitHours": 8.0,
    "solReserve": 0.032,
    "ageGateMinutes": 5.0,
    "drawdownWarning": 0.15,
    "drawdownHalt": 0.2
  },
  "risk": {
    "breakerStatus": "nominal",
    "peakBalance": 42.2289301336,
    "position": null,
    "blacklistCount": 1
  },
  "bobnet": {
    "status": "online",
    "uptime": 5161,
    "restarts": 33,
    "signals_today": 26,
    "signals_total": 50
  },
  "bot": {
    "status": "online",
    "uptime": 2392,
    "restarts": 46,
    "pid": 748976,
    "heap_mb": 101.8,
    "queue_size": 0
  },
  "performance": {
    "totalTrades": 0,
    "wins": 0,
    "losses": 0,
    "grossPnl": 0,
    "feesPaid": 0
  },
  "trades": [],
  "processes": {
    "bot-api": {
      "name": "bot-api",
      "status": "online",
      "uptime": 84548,
      "restarts": 0,
      "pid": 578341,
      "heap_mb": 64.7
    },
    "bot-tunnel": {
      "name": "bot-tunnel",
      "status": "online",
      "uptime": 60672,
      "restarts": 1,
      "pid": 631968,
      "heap_mb": 3.1
    },
    "data-service": {
      "name": "data-service",
      "status": "online",
      "uptime": 84548,
      "restarts": 0,
      "pid": 578362,
      "heap_mb": 90.5
    },
    "athena-bot-v2": {
      "name": "athena-bot-v2",
      "status": "online",
      "uptime": 2392,
      "restarts": 46,
      "pid": 748976,
      "heap_mb": 101.8
    },
    "thor-dashboard": {
      "name": "thor-dashboard",
      "status": "online",
      "uptime": 10210,
      "restarts": 39,
      "pid": 732428,
      "heap_mb": 40.2
    },
    "thor-tunnel": {
      "name": "thor-tunnel",
      "status": "online",
      "uptime": 60672,
      "restarts": 1,
      "pid": 631964,
      "heap_mb": 36.7
    },
    "nginx-proxy": {
      "name": "nginx-proxy",
      "status": "online",
      "uptime": 68313,
      "restarts": 44,
      "pid": 612311,
      "heap_mb": 3.1
    },
    "bobnet-listener-v2": {
      "name": "bobnet-listener-v2",
      "status": "online",
      "uptime": 5161,
      "restarts": 33,
      "pid": 743238,
      "heap_mb": 73.0
    },
    "sentiment-engine": {
      "name": "sentiment-engine",
      "status": "online",
      "uptime": 80174,
      "restarts": 1,
      "pid": 590362,
      "heap_mb": 23.5
    },
    "vercel-sync": {
      "name": "vercel-sync",
      "status": "online",
      "uptime": 76887,
      "restarts": 0,
      "pid": 597915,
      "heap_mb": 13.2
    },
    "dashboard-tunnel": {
      "name": "dashboard-tunnel",
      "status": "online",
      "uptime": 59851,
      "restarts": 0,
      "pid": 633738,
      "heap_mb": 38.7
    },
    "pumpfun-sniper": {
      "name": "pumpfun-sniper",
      "status": "online",
      "uptime": 53582,
      "restarts": 0,
      "pid": 653695,
      "heap_mb": 89.4
    },
    "wallet-scanner": {
      "name": "wallet-scanner",
      "status": "online",
      "uptime": 47502,
      "restarts": 6,
      "pid": 675127,
      "heap_mb": 111.2
    },
    "omega-remediation-daemon": {
      "name": "omega-remediation-daemon",
      "status": "online",
      "uptime": 10161,
      "restarts": 1,
      "pid": 732567,
      "heap_mb": 15.0
    }
  },
  "session_pnl": {
    "daily_pnl": 0,
    "daily_trades": 0,
    "daily_wins": 0,
    "daily_losses": 0,
    "date": "2026-05-16"
  },
  "quantum": {
    "jito": {
      "status": "Framework Ready",
      "rpc": "Public (simulation mode)",
      "tip_sol": "0.000010",
      "land_rate_pct": 95,
      "congestion": "LOW",
      "total_simulations": 0
    },
    "alpha_sources": {
      "telegram": {
        "status": "ACTIVE",
        "channels": 2,
        "names": [
          "The Printer ICM - Beta",
          "The Printer by BobnetAI - Official"
        ]
      },
      "dexscreener": {
        "last_update": "2026-05-16T10:21:13.675463+00:00",
        "total_tokens": 53,
        "boosted": 30,
        "trending": 26,
        "cache_file": "/opt/solana-bot-v2/data/trending_cache.json",
        "status": "ACTIVE"
      }
    },
    "dynamic_risk": {
      "mode": "warm-up",
      "virtual_trades": 3,
      "virtual_win_rate": 0.6667,
      "real_trades": 0,
      "current_size_usd": 5.0,
      "risk_tier": "Conservative"
    },
    "signal_fusion": {
      "enabled": true,
      "boost_on_trending": 10,
      "boost_on_boosted": 15,
      "cache_tokens": 53
    }
  },
  "rug_shield": {
    "enabled": true,
    "last_audit": [
      {
        "timestamp": "2026-05-16T05:07:57.348Z",
        "tokenMint": "DkaY3z9hYutckCNoLCy8kfJvrDEDwjojQ9zL1s4Fpump",
        "passed": false,
        "reason": "Top holder owns 21.7% (>15% danger)",
        "checks": {
          "mintRenounced": true,
          "liquidityLocked": false,
          "topHolderPct": 21.74286257538603,
          "topHolderOk": false,
          "topHolderLevel": "danger"
        }
      }
    ],
    "total_audits": 8,
    "total_blocked": 8,
    "checks": [
      "mint_renounced",
      "top_holder_<10%",
      "no_danger_risks"
    ]
  }
}